crypticbio_curate/__init__.py
crypticbio_curate/crypticbio_curate.py
crypticbio_curate/image_download.py
crypticbio_curate/metadata_loader.py
crypticbio-0.3.0.dist-info/LICENSE
crypticbio-0.3.0.dist-info/METADATA
crypticbio-0.3.0.dist-info/WHEEL
crypticbio-0.3.0.dist-info/RECORD
