Metadata-Version: 2.3
Name: crypticbio
Version: 0.3.0
Summary: CrypticBio: A Large Multimodal Dataset for Visually Confusing Biodiversity
License: CC-BY-4.0
Keywords: biodiversity,multimodal,dataset,vision,confusing species
Author: Georgiana Manolache
Requires-Python: >=3.9,<4.0
Classifier: Development Status :: 4 - Beta
Classifier: Intended Audience :: Developers
Classifier: Intended Audience :: Science/Research
Classifier: License :: Other/Proprietary License
Classifier: Natural Language :: English
Classifier: Programming Language :: Python :: 3
Classifier: Programming Language :: Python :: 3.9
Classifier: Programming Language :: Python :: 3.10
Classifier: Programming Language :: Python :: 3.11
Classifier: Programming Language :: Python :: 3.12
Classifier: Programming Language :: Python :: 3.13
Classifier: Topic :: Scientific/Engineering :: Information Analysis
Requires-Dist: datasets
Requires-Dist: requests
Project-URL: Documentation, https://georgianagmanolache.github.io/crypticbio
Project-URL: Homepage, https://georgianagmanolache.github.io/crypticbio
Project-URL: Repository, https://github.com/georgianagmanolache/crypticbio
